tweet_images/__init__.py
tweet_images/cli.py
tweet_images-0.1.2.dist-info/LICENSE
tweet_images-0.1.2.dist-info/METADATA
tweet_images-0.1.2.dist-info/WHEEL
tweet_images-0.1.2.dist-info/entry_points.txt
tweet_images-0.1.2.dist-info/top_level.txt
tweet_images-0.1.2.dist-info/RECORD
