Metadata-Version: 2.1
Name: tweet-images
Version: 0.1.2
Summary: Send tweets with images from the command line
Home-page: https://github.com/simonw/tweet-images
Author: Simon Willison
License: Apache License, Version 2.0
Project-URL: Issues, https://github.com/simonw/tweet-images/issues
Project-URL: CI, https://github.com/simonw/tweet-images/actions
Project-URL: Changelog, https://github.com/simonw/tweet-images/releases
Platform: UNKNOWN
Requires-Python: >=3.7
License-File: LICENSE
Requires-Dist: click
Requires-Dist: python-twitter
Provides-Extra: test
Requires-Dist: pytest ; extra == 'test'
